pathconf/__init__.py
pathconf/pathconf.py
pathconf-1.0.10.6.dist-info/METADATA
pathconf-1.0.10.6.dist-info/WHEEL
pathconf-1.0.10.6.dist-info/top_level.txt
pathconf-1.0.10.6.dist-info/RECORD
