Metadata-Version: 2.1
Name: pathconf
Version: 1.0.10.6
Summary: Uses os.walk to find and catalogue a given file.
Author: Sam Kirby
Author-email: sam.kirby@gagamuller.com
Classifier: Programming Language :: Python :: 3
Classifier: License :: OSI Approved :: MIT License
Classifier: Operating System :: OS Independent
Requires-Python: >=3.1
